PlatynUI/__about__.py
PlatynUI/__init__.py
PlatynUI/py.typed
PlatynUI/core/__init__.py
PlatynUI/core/adapter.py
PlatynUI/core/adapterfactory.py
PlatynUI/core/adapterproxy.py
PlatynUI/core/contextbase.py
PlatynUI/core/ensure.py
PlatynUI/core/exceptions.py
PlatynUI/core/locatorbase.py
PlatynUI/core/locatorscope.py
PlatynUI/core/predicate.py
PlatynUI/core/settings.py
PlatynUI/core/strategybase.py
PlatynUI/core/strategyimpl.py
PlatynUI/core/technology.py
PlatynUI/core/types.py
PlatynUI/core/wait_for.py
PlatynUI/core/weight_calculator.py
PlatynUI/core/internal/__init__.py
PlatynUI/core/internal/decorator.py
PlatynUI/core/strategies/__init__.py
PlatynUI/core/strategies/strategies.py
PlatynUI/keywords/__init__.py
PlatynUI/keywords/activatable.py
PlatynUI/keywords/application.py
PlatynUI/keywords/assertable.py
PlatynUI/keywords/keyboard.py
PlatynUI/keywords/mouse.py
PlatynUI/keywords/properties.py
PlatynUI/keywords/text.py
PlatynUI/keywords/types.py
PlatynUI/keywords/wait.py
PlatynUI/robot/__init__.py
PlatynUI/robot/reporting.py
PlatynUI/spy/__init__.py
PlatynUI/spy/__main__.py
PlatynUI/technology/__init__.py
PlatynUI/technology/uiautomation/.gitignore
PlatynUI/technology/uiautomation/__init__.py
PlatynUI/technology/uiautomation/desktop.py
PlatynUI/technology/uiautomation/locator.py
PlatynUI/technology/uiautomation/core/adapterfactory.py
PlatynUI/technology/uiautomation/core/displaydevice.py
PlatynUI/technology/uiautomation/core/keyboarddevice.py
PlatynUI/technology/uiautomation/core/loader.py
PlatynUI/technology/uiautomation/core/mousedevice.py
PlatynUI/technology/uiautomation/core/technology.py
PlatynUI/technology/uiautomation/core/uiaadapter.py
PlatynUI/technology/uiautomation/core/uiabase.py
PlatynUI/technology/uiautomation/core/impls/__init__.py
PlatynUI/technology/uiautomation/core/impls/control.py
PlatynUI/technology/uiautomation/core/impls/window.py
PlatynUI/technology/uiautomation/spy/__init__.py
robotframework_platynui-0.9.2.dist-info/METADATA
robotframework_platynui-0.9.2.dist-info/WHEEL
robotframework_platynui-0.9.2.dist-info/entry_points.txt
robotframework_platynui-0.9.2.dist-info/RECORD
robotframework_platynui-0.9.2.dist-info/licenses/LICENSE.txt
