Metadata-Version: 2.4
Name: robotframework-platynui
Version: 0.9.2
Summary: PlatynUI is a library for Robot Framework that enables easy and cross-platform desktop UI automation with a comprehensive set of keywords for interacting with desktop applications.
Project-URL: Documentation, https://github.com/imbus/robotframework-platynui#readme
Project-URL: Issues, https://github.com/imbus/robotframework-platynui/issues
Project-URL: Source, https://github.com/imbus/robotframework-platynui
Author-email: Daniel Biehl <daniel.biehl@imbus.de>
License: Apache-2.0
License-File: LICENSE.txt
Classifier: Development Status :: 3 - Alpha
Classifier: Framework :: Robot Framework :: Library
Classifier: Intended Audience :: Developers
Classifier: Programming Language :: C#
Classifier: Programming Language :: Python
Classifier: Programming Language :: Python :: 3.10
Classifier: Programming Language :: Python :: 3.11
Classifier: Programming Language :: Python :: 3.12
Classifier: Programming Language :: Python :: 3.13
Classifier: Programming Language :: Python :: Implementation :: CPython
Requires-Python: <3.14,>=3.10
Requires-Dist: pythonnet>=3.0.0
Requires-Dist: robotframework-assertion-engine>=3.0.0
Requires-Dist: robotframework-pythonlibcore>=4.4.0
Requires-Dist: robotframework>=6.0.0
Requires-Dist: typing-extensions
